LICENSE
MANIFEST.in
README.md
setup.py
scipy_quadopt/__init__.py
scipy_quadopt/problem.py
scipy_quadopt/utils.py
scipy_quadopt.egg-info/PKG-INFO
scipy_quadopt.egg-info/SOURCES.txt
scipy_quadopt.egg-info/dependency_links.txt
scipy_quadopt.egg-info/requires.txt
scipy_quadopt.egg-info/top_level.txt
scipy_quadopt.egg-info/zip-safe
test/__init__.py
test/test_aggregate_matrices.py
test/test_get_weights.py