Metadata-Version: 2.1
Name: scipy-quadopt
Version: 0.2.0
Summary: Wrapper and utility functions to apply scipy's SLSQP algorithm to quadratic optimization problems with resource constraints and upper boundaries.
Home-page: http://github.com/ulf1/scipy-quadopt
Author: Ulf Hamster
Author-email: 554c46@gmail.com
License: Apache License 2.0
Platform: UNKNOWN
Requires-Python: >=3.6
License-File: LICENSE
